orthanc_launcher
