Metadata-Version: 1.0
Name: orthanc-launcher
Version: 0.1.3
Summary: Helpers class to launch Orthanc servers on Windows/Linux/OSX.
Home-page: https://bitbucket.org/osimis/python-orthanc-launcher
Author: Alain Mazy
Author-email: am@osimis.io
License: UNKNOWN
Keywords: orthanc,launcher
Platform: UNKNOWN
